nopy/__init__.py
nopy/client.py
nopy/constants.py
nopy/enums.py
nopy/errors.py
nopy/filters.py
nopy/objects/__init__.py
nopy/objects/database.py
nopy/objects/notion_object.py
nopy/objects/page.py
nopy/objects/user.py
nopy/properties.py
nopy/props/__init__.py
nopy/props/base.py
nopy/props/common.py
nopy/props/db_props.py
nopy/props/page_props.py
nopy/query.py
nopy/sorts.py
nopy/types.py
nopy/utils.py
notion_nopy-0.1.0.dist-info/LICENSE.md
notion_nopy-0.1.0.dist-info/WHEEL
notion_nopy-0.1.0.dist-info/METADATA
notion_nopy-0.1.0.dist-info/RECORD
