Metadata-Version: 2.1
Name: notion-nopy
Version: 0.1.0
Summary: An unofficial OOP interface for the Notion API.
License: MIT
Author: Visakh Unnikrishnan
Author-email: visakhcu96@gmail.com
Requires-Python: >=3.8.1,<4.0.0
Classifier: License :: OSI Approved :: MIT License
Classifier: Programming Language :: Python :: 3
Classifier: Programming Language :: Python :: 3.9
Classifier: Programming Language :: Python :: 3.10
Classifier: Programming Language :: Python :: 3.11
Requires-Dist: httpx (>=0.23.1,<0.24.0)
Requires-Dist: python-dateutil (>=2.8.2,<3.0.0)
